poetry_plugin_lockedbuild/__init__.py
poetry_plugin_lockedbuild/builder.py
poetry_plugin_lockedbuild/command.py
poetry_plugin_lockedbuild/plugins.py
poetry_plugin_lockedbuild-0.10.1.dist-info/LICENSE
poetry_plugin_lockedbuild-0.10.1.dist-info/METADATA
poetry_plugin_lockedbuild-0.10.1.dist-info/WHEEL
poetry_plugin_lockedbuild-0.10.1.dist-info/entry_points.txt
poetry_plugin_lockedbuild-0.10.1.dist-info/RECORD
