Metadata-Version: 2.1
Name: poetry-plugin-lockedbuild
Version: 0.10.1
Summary: Poetry plugin to add support for building wheel files with locked packages from the poetry.lock
Home-page: https://github.com/thesnapdragon/poetry-plugin-lockedbuild
License: MIT
Keywords: python,poetry,poetry-plugin
Author: Milan Unicsovics
Author-email: u.milan@gmail.com
Requires-Python: >=3.8,<4.0
Classifier: License :: OSI Approved :: MIT License
Classifier: Programming Language :: Python :: 3
Classifier: Programming Language :: Python :: 3.8
Classifier: Programming Language :: Python :: 3.9
Classifier: Programming Language :: Python :: 3.10
Classifier: Programming Language :: Python :: 3.11
Requires-Dist: poetry (>=1.5,<2.0)
Project-URL: Repository, https://github.com/thesnapdragon/poetry-plugin-lockedbuild
